README.md
setup.py
gemf/__init__.py
gemf/caller.py
gemf/decorators.py
gemf/interaction_functions.py
gemf/models.py
gemf/plot.py
gemf/worker.py
gemf.egg-info/PKG-INFO
gemf.egg-info/SOURCES.txt
gemf.egg-info/dependency_links.txt
gemf.egg-info/requires.txt
gemf.egg-info/top_level.txt
tests/__init__.py
tests/conftest.py
tests/test_forward.py
tests/test_import.py
tests/test_inverse.py
tests/test_visualisation.py