Metadata-Version: 2.1
Name: gemf
Version: 0.3.1
Summary: General Ecosystem Modelling Framework
Home-page: https://github.com/465b/General-Ecosystem-Modeling-Framework/
Author: Laurin Steidle
Author-email: laurin.steidle@uni-hamburg.de
License: BSD
Keywords: ecosystem modelling framework inverse-modelling
Platform: UNKNOWN
Classifier: License :: OSI Approved :: BSD License
Classifier: Programming Language :: Python :: 3
Classifier: Topic :: Scientific/Engineering
Classifier: Intended Audience :: Science/Research
Classifier: Operating System :: POSIX :: Linux
Classifier: Development Status :: 3 - Alpha
